README.rst
setup.py
locatebash/__init__.py
locatebash.egg-info/PKG-INFO
locatebash.egg-info/SOURCES.txt
locatebash.egg-info/dependency_links.txt
locatebash.egg-info/entry_points.txt
locatebash.egg-info/requires.txt
locatebash.egg-info/top_level.txt
locatebash.egg-info/zip-safe