Metadata-Version: 1.1
Name: locatebash
Version: 9
Summary: Combines mdfind and locate
Home-page: https://github.com/erikdejonge/locatebash
Author: Erik de Jonge
Author-email: erik@a8.nl
License: GPL
Platform: UNKNOWN
Classifier: Programming Language :: Python :: 2
Classifier: Intended Audience :: Developers
Classifier: License :: OSI Approved :: GNU Library or Lesser General Public License (LGPL)
Classifier: Operating System :: POSIX
Classifier: Environment :: MacOS X
Classifier: Topic :: System
